cult/__init__.py
cult/util.py
cult/sources/__init__.py
cult/sources/bible.py
cult/sources/king_james_bible.py
cult/sources/quaran.py
cult-0.0.3.dist-info/LICENSE
cult-0.0.3.dist-info/METADATA
cult-0.0.3.dist-info/WHEEL
cult-0.0.3.dist-info/top_level.txt
cult-0.0.3.dist-info/RECORD
