Metadata-Version: 2.1
Name: cult
Version: 0.0.3
Summary: Religious texts search engine
Home-page: https://github.com/thorwhalen/cult
Author: Thor Whalen
License: mit
Platform: any
Requires-Dist: graze
Requires-Dist: grub
Requires-Dist: py2store
